MANIFEST.in
README.md
setup.py
ddreport/__init__.py
ddreport/api.py
ddreport/db.py
ddreport/exceptd.py
ddreport/func.py
ddreport/handle.py
ddreport.egg-info/PKG-INFO
ddreport.egg-info/SOURCES.txt
ddreport.egg-info/dependency_links.txt
ddreport.egg-info/entry_points.txt
ddreport.egg-info/requires.txt
ddreport.egg-info/top_level.txt
ddreport/template/index.html