Metadata-Version: 2.4
Name: ddreport
Version: 4.6.4
Summary: pytest测试报告 1.修改测试报告模板
Home-page: https://zhuanlan.zhihu.com/p/692810160
Author: duanliangcong
Author-email: 137562703@qq.com
License: MIT Licence
Classifier: Framework :: Pytest
Classifier: Programming Language :: Python
Classifier: Topic :: Software Development :: Testing
Requires-Dist: requests
Requires-Dist: sshtunnel
Requires-Dist: pymysql
Requires-Dist: psycopg2
Requires-Dist: jsonpath
Requires-Dist: openpyxl
Requires-Dist: deepdiff
Requires-Dist: python-dateutil
Dynamic: author
Dynamic: author-email
Dynamic: classifier
Dynamic: description
Dynamic: description-content-type
Dynamic: home-page
Dynamic: license
Dynamic: requires-dist
Dynamic: summary
